README.rst
setup.py
sphinxcontrib/__init__.py
sphinxcontrib/ocaml/__init__.py
sphinxcontrib/ocaml/autodocumenters.py
sphinxcontrib/ocaml/domain.py
sphinxcontrib_ocaml.egg-info/PKG-INFO
sphinxcontrib_ocaml.egg-info/SOURCES.txt
sphinxcontrib_ocaml.egg-info/dependency_links.txt
sphinxcontrib_ocaml.egg-info/namespace_packages.txt
sphinxcontrib_ocaml.egg-info/top_level.txt