Metadata-Version: 1.1
Name: sphinxcontrib-ocaml
Version: 0.3.0
Summary: Sphinx extension to document OCaml libraries
Home-page: http://jacquev6.github.io/sphinxcontrib-ocaml/
Author: Vincent Jacques
Author-email: vincent@vincent-jacques.net
License: MIT
Platform: UNKNOWN
Classifier: Development Status :: 2 - Pre-Alpha
Classifier: Intended Audience :: Developers
Classifier: License :: OSI Approved
Classifier: License :: OSI Approved :: MIT License
Classifier: Operating System :: OS Independent
Classifier: Programming Language :: Python
Classifier: Programming Language :: OCaml
Classifier: Topic :: Documentation
Classifier: Topic :: Documentation :: Sphinx
